{
    "NAME_TEST_NPC": {
        "TextData": {
            "Namespace": "DT_HumanNameText",
            "Key": "NAME_TEST_NPC_TextData",
            "SourceString": "テスト用NPC",
            "LocalizedString": "テスト用NPC"
        }
    },
    "NAME_CITIZEN": {
        "TextData": {
            "Namespace": "DT_HumanNameText",
            "Key": "NAME_CITIZEN_TextData",
            "SourceString": "島民",
            "LocalizedString": "島民"
        }
    },
    "NAME_VILLAGER": {
        "TextData": {
            "Namespace": "DT_HumanNameText",
            "Key": "NAME_VILLAGER_TextData",
            "SourceString": "村人",
            "LocalizedString": "村人"
        }
    },
    "NAME_QUESTMAN": {
        "TextData": {
            "Namespace": "DT_HumanNameText",
            "Key": "NAME_QUESTMAN_TextData",
            "SourceString": "クエストマン",
            "LocalizedString": "クエストマン"
        }
    },
    "NAME_SELESPERSON": {
        "TextData": {
            "Namespace": "DT_HumanNameText",
            "Key": "NAME_SELESPERSON_TextData",
            "SourceString": "放浪商人",
            "LocalizedString": "放浪商人"
        }
    },
    "NAME_VISITING": {
        "TextData": {
            "Namespace": "DT_HumanNameText",
            "Key": "NAME_VISITING_TextData",
            "SourceString": "来訪者",
            "LocalizedString": "来訪者"
        }
    },
    "NAME_WEAPON_DEALER": {
        "TextData": {
            "Namespace": "DT_HumanNameText",
            "Key": "NAME_WEAPON_DEALER_TextData",
            "SourceString": "武器商人",
            "LocalizedString": "武器商人"
        }
    },
    "NAME_PAL_DEALER": {
        "TextData": {
            "Namespace": "DT_HumanNameText",
            "Key": "NAME_PAL_DEALER_TextData",
            "SourceString": "パル商人",
            "LocalizedString": "パル商人"
        }
    },
    "NAME_GUARD": {
        "TextData": {
            "Namespace": "DT_HumanNameText",
            "Key": "NAME_GUARD_TextData",
            "SourceString": "衛兵",
            "LocalizedString": "衛兵"
        }
    },
    "NAME_SecurityDrone": {
        "TextData": {
            "Namespace": "DT_HumanNameText",
            "Key": "NAME_SecurityDrone_TextData",
            "SourceString": "監視ドローン",
            "LocalizedString": "監視ドローン"
        }
    },
    "NAME_Believer": {
        "TextData": {
            "Namespace": "DT_HumanNameText",
            "Key": "NAME_Believer_TextData",
            "SourceString": "パル愛護団体 信者",
            "LocalizedString": "パル愛護団体 信者"
        }
    },
    "NAME_FireCult": {
        "TextData": {
            "Namespace": "DT_HumanNameText",
            "Key": "NAME_FireCult_TextData",
            "SourceString": "永炎の同志 殉教者",
            "LocalizedString": "永炎の同志 殉教者"
        }
    },
    "NAME_Labmen": {
        "TextData": {
            "Namespace": "DT_HumanNameText",
            "Key": "NAME_Labmen_TextData",
            "SourceString": "遺伝子研究部隊 実行班",
            "LocalizedString": "遺伝子研究部隊 実行班"
        }
    },
    "NAME_POLICE": {
        "TextData": {
            "Namespace": "DT_HumanNameText",
            "Key": "NAME_POLICE_TextData",
            "SourceString": "自警団 ガード",
            "LocalizedString": "自警団 ガード"
        }
    },
    "NAME_POLICE_1": {
        "TextData": {
            "Namespace": "DT_HumanNameText",
            "Key": "NAME_POLICE_1_TextData",
            "SourceString": "自警団 パトローラー",
            "LocalizedString": "自警団 パトローラー"
        }
    },
    "NAME_POLICE_2": {
        "TextData": {
            "Namespace": "DT_HumanNameText",
            "Key": "NAME_POLICE_2_TextData",
            "SourceString": "自警団 ライフルマン",
            "LocalizedString": "自警団 ライフルマン"
        }
    },
    "NAME_POLICE_3": {
        "TextData": {
            "Namespace": "DT_HumanNameText",
            "Key": "NAME_POLICE_3_TextData",
            "SourceString": "自警団 エリート",
            "LocalizedString": "自警団 エリート"
        }
    },
    "NAME_HUNTER": {
        "TextData": {
            "Namespace": "DT_HumanNameText",
            "Key": "NAME_HUNTER_TextData",
            "SourceString": "密猟団 ルーキー",
            "LocalizedString": "密猟団 ルーキー"
        }
    },
    "NAME_HUNTER_2": {
        "TextData": {
            "Namespace": "DT_HumanNameText",
            "Key": "NAME_HUNTER_2_TextData",
            "SourceString": "密猟団 ガンナー",
            "LocalizedString": "密猟団 ガンナー"
        }
    },
    "NAME_HUNTER_3": {
        "TextData": {
            "Namespace": "DT_HumanNameText",
            "Key": "NAME_HUNTER_3_TextData",
            "SourceString": "密猟団 ハンター",
            "LocalizedString": "密猟団 ハンター"
        }
    },
    "NAME_HUNTER_4": {
        "TextData": {
            "Namespace": "DT_HumanNameText",
            "Key": "NAME_HUNTER_4_TextData",
            "SourceString": "密猟団 グレネーダー",
            "LocalizedString": "密猟団 グレネーダー"
        }
    },
    "NAME_HUNTER_5": {
        "TextData": {
            "Namespace": "DT_HumanNameText",
            "Key": "NAME_HUNTER_5_TextData",
            "SourceString": "密猟団 クリーナー",
            "LocalizedString": "密猟団 クリーナー"
        }
    },
    "NAME_HUNTER_6": {
        "TextData": {
            "Namespace": "DT_HumanNameText",
            "Key": "NAME_HUNTER_6_TextData",
            "SourceString": "密猟団 エリート",
            "LocalizedString": "密猟団 エリート"
        }
    },
    "NAME_HUNTER_BOSS": {
        "TextData": {
            "Namespace": "DT_HumanNameText",
            "Key": "NAME_HUNTER_BOSS_TextData",
            "SourceString": "密猟団 クラッシャー",
            "LocalizedString": "密猟団 クラッシャー"
        }
    }
}